potatotime/__init__.py
potatotime/storage.py
potatotime/synchronize.py
potatotime/services/__init__.py
potatotime/services/auth.py
potatotime/services/gcal.py
potatotime/services/ical.py
potatotime/services/outlook.py
potatotime-0.0.6.dist-info/licenses/LICENSE
potatotime-0.0.6.dist-info/METADATA
potatotime-0.0.6.dist-info/WHEEL
potatotime-0.0.6.dist-info/top_level.txt
potatotime-0.0.6.dist-info/RECORD
