Metadata-Version: 2.4
Name: potatotime
Version: 0.0.6
Summary: Synchronize events between Google, Outlook, and iCal.
Author: Alvin Wan
Project-URL: Homepage, https://github.com/alvinwan/potatotime
Project-URL: Repository, https://github.com/alvinwan/potatotime
Project-URL: Issues, https://github.com/alvinwan/potatotime/issues
Requires-Python: >=3.8
License-File: LICENSE
Requires-Dist: oauth2client
Requires-Dist: caldav
Requires-Dist: requests
Requires-Dist: google-api-python-client
Requires-Dist: google-auth-httplib2
Requires-Dist: google-auth-oauthlib
Requires-Dist: pytz
Requires-Dist: msal
Provides-Extra: test
Requires-Dist: pytest; extra == "test"
Requires-Dist: pytest-cov; extra == "test"
Dynamic: license-file
